[
  {
    "id":1,
    "name": "Bistrot des Gasçons",
    "image":"../../assets/picture/restaurant1.jpeg",
    "adresse":"42 Rue de la Mer Imaginaire, 75001 Paris",
    "description": [
      "Quil est chaud le solei",
      "Quand nous sommes en vacances",
      "Y a d lajoie, dee hirondelles",
      "Castle sud de la Frande Papa briesie au garage",
      "Maman it dans la chaise longue",
      "Dana ce jol paysage",
      "Moi je me balade en tongs",
      "Que de bonheur!",
      "Que de bonheur!"
    ]
  },
  {
    "id":2,
    "name": "Les fous de l'île",
    "image":"../../assets/picture/restaurant2.jpeg",
    "adresse":"18 Quai des Saveurs Marines, 75004 Paris",
    "description": [
      "Quil est chaud le solei",
      "Quand nous sommes en vacances",
      "Y a d lajoie, dee hirondelles",
      "Castle sud de la Frande Papa briesie au garage",
      "Maman it dans la chaise longue",
      "Dana ce jol paysage",
      "Moi je me balade en tongs",
      "Que de bonheur!",
      "Que de bonheur!"
    ]
  },
  {
    "id":3,
    "name": "Bistrot Landais",
    "image":"../../assets/picture/restaurant3.jpeg",
    "adresse":"8 Rue des Marées Salées, 75007 Paris",
    "description": [
      "Quil est chaud le solei",
      "Quand nous sommes en vacances",
      "Y a d lajoie, dee hirondelles",
      "Castle sud de la Frande Papa briesie au garage",
      "Maman it dans la chaise longue",
      "Dana ce jol paysage",
      "Moi je me balade en tongs",
      "Que de bonheur!",
      "Que de bonheur!"
    ]
  },
  {
    "id":4,
    "name": "Villas 9-Trois",
    "image":"../../assets/picture/restaurant4.jpeg",
    "adresse":"33 Rue des Poissons Frais, 75010 Paris",
    "description": [
      "Quil est chaud le solei",
      "Quand nous sommes en vacances",
      "Y a d lajoie, dee hirondelles",
      "Castle sud de la Frande Papa briesie au garage",
      "Maman it dans la chaise longue",
      "Dana ce jol paysage",
      "Moi je me balade en tongs",
      "Que de bonheur!",
      "Que de bonheur!"
    ]
  },
  {
    "id":5,
    "name": "Bistrot du Sommelier",
    "image":"../../assets/picture/restaurant5.jpg",
    "adresse":"56 Avenue des Saveurs Marines, 75016 Paris",
    "description": [
      "Quil est chaud le solei",
      "Quand nous sommes en vacances",
      "Y a d lajoie, dee hirondelles",
      "Castle sud de la Frande Papa briesie au garage",
      "Maman it dans la chaise longue",
      "Dana ce jol paysage",
      "Moi je me balade en tongs",
      "Que de bonheur!",
      "Que de bonheur!"
    ]
  }
]